phishnet_api_v4/__init__.py
phishnet_api_v4/api_client.py
phishnet_api_v4/decorators.py
phishnet_api_v4/exceptions.py
phishnet_api_v4/settings.py
phishnet_api_v4/validators.py
phishnet_api_v4-0.1.0.dist-info/LICENSE
phishnet_api_v4-0.1.0.dist-info/WHEEL
phishnet_api_v4-0.1.0.dist-info/METADATA
phishnet_api_v4-0.1.0.dist-info/RECORD
